scematics_cli/__init__.py
scematics_cli/cli.py
scematics_cli/custom_upload.py
scematics_cli/custom_upload_buckets.py
scematics_cli/custom_upload_local.py
scematics_cli/direct_upload.py
scematics_cli/folder_uploads.py
scematics_cli/tag_uploads.py
scematics_cli-0.1.22.dist-info/METADATA
scematics_cli-0.1.22.dist-info/WHEEL
scematics_cli-0.1.22.dist-info/entry_points.txt
scematics_cli-0.1.22.dist-info/top_level.txt
scematics_cli-0.1.22.dist-info/RECORD
