Metadata-Version: 2.4
Name: scematics-cli
Version: 0.1.22
Summary: A CLI tool for managing file uploads
Home-page: https://github.com/0karthickm/scematics-cli
Author: scematics.io
Author-email: karthickeyan@scematics.xyz
Classifier: Programming Language :: Python :: 3
Classifier: License :: OSI Approved :: MIT License
Classifier: Operating System :: OS Independent
Requires-Python: >=3.10
Requires-Dist: typer
Requires-Dist: requests
Requires-Dist: rich
Requires-Dist: pillow
Requires-Dist: opencv-python
Requires-Dist: pathlib
Requires-Dist: websocket-client
Requires-Dist: websockets
Requires-Dist: tqdm
Requires-Dist: boto3
Requires-Dist: azure-storage-blob
Requires-Dist: google-cloud-storage
Dynamic: author
Dynamic: author-email
Dynamic: classifier
Dynamic: description
Dynamic: description-content-type
Dynamic: home-page
Dynamic: requires-dist
Dynamic: requires-python
Dynamic: summary
